domaincheck/__init__.py
domaincheck/domaincheck.py
domaincheck_fork-0.5.2.data/data/share/man/man1/domaincheck.1
domaincheck_fork-0.5.2.data/scripts/domaincheck.py
domaincheck_fork-0.5.2.dist-info/LICENSE
domaincheck_fork-0.5.2.dist-info/METADATA
domaincheck_fork-0.5.2.dist-info/WHEEL
domaincheck_fork-0.5.2.dist-info/top_level.txt
domaincheck_fork-0.5.2.dist-info/RECORD
