Metadata-Version: 2.1
Name: domaincheck-fork
Version: 0.5.2
Summary: check security aspects of a second-level domain name
Home-page: https://github.com/intelowlproject/domaincheck/
Author: Jan Schaumann, Zuza Slawik
Author-email: jschauma@akamai.com, zslawik@akamai.com
License: Apache
Keywords: CAA DMARC DNS DNSKEY DNSSEC MTA-STS SPF TLS-RPT
License-File: LICENSE
Requires-Dist: cryptography >=3.3.2
Requires-Dist: dnspython >=2.2.1
